ljj/__init__.py
ljj/handsome/__init__.py
ljj/handsome/boy/__init__.py
ljj/handsome/boy/message.py
helloljj-0.1.0.dist-info/METADATA
helloljj-0.1.0.dist-info/WHEEL
helloljj-0.1.0.dist-info/top_level.txt
helloljj-0.1.0.dist-info/RECORD
