Metadata-Version: 2.1
Name: helloljj
Version: 0.1.0
Summary: the team 's member just only one  
Home-page: UNKNOWN
Author: ljj
Author-email: 1498283571@qq.com
License: UNKNOWN
Platform: UNKNOWN
